docker_nuke-0.2.2.dist-info/METADATA
docker_nuke-0.2.2.dist-info/RECORD
docker_nuke-0.2.2.dist-info/WHEEL
docker_nuke-0.2.2.dist-info/entry_points.txt
docker_nuke-0.2.2.dist-info/pbr.json
docker_nuke-0.2.2.dist-info/top_level.txt
dockernuke/__init__.py
dockernuke/cli.py
dockernuke/main.py
