Metadata-Version: 2.1
Name: docker-nuke
Version: 0.2.2
Summary: Remove all Docker containers, images, and volumes
Home-page: https://github.com/levi-rs/docker-nuke
Author: Levi Noecker
Author-email: levi.noecker@gmail.com
License: MIT
Keywords: docker docker-utils
Platform: UNKNOWN
Classifier: Development Status :: 4 - Beta
Classifier: Environment :: Console
Classifier: Intended Audience :: Developers
Classifier: License :: OSI Approved :: MIT License
Classifier: Operating System :: OS Independent
Classifier: Programming Language :: Python
Classifier: Programming Language :: Python :: 2
Classifier: Programming Language :: Python :: 2.7
Classifier: Programming Language :: Python :: 3
Classifier: Programming Language :: Python :: 3.4
Classifier: Programming Language :: Python :: 3.5
Classifier: Programming Language :: Python :: 3.6
Classifier: Programming Language :: Python :: Implementation :: CPython
Requires-Dist: click
Requires-Dist: docker
Requires-Dist: pbr (>=3.0)
